Workbook

Sheet Sheet1
A2: Cash Up Sheet
B4: 41897 | C4: =B4+1 -> 41898 | D4: =C4+1 -> 41899 | E4: =D4+1 -> 41900 | F4: =E4+1 -> 41901 | G4: =F4+1 -> 41902 | H4: =G4+1 -> 41903 | I4: =H4+1 -> 41904 | J4: =I4+1 -> 41905 | ... Q4: =P4+1 -> 41912
A5: TILL FLOAT
A6: 0.01
A7: 0.05
A8: 0.2
A9: 0.5
A10: 1
A11: 2
A12: 5
A13: 10
A14: 20
A15: Total | B15: =SUM(B6:B14) -> 0 | C15: =SUM(C6:C14) -> 0 | D15: =SUM(D6:D14) -> 0 | E15: =SUM(E6:E14) -> 0 | F15: =SUM(F6:F14) -> 0 | G15: =SUM(G6:G14) -> 0 | H15: =SUM(H6:H14) -> 0 | I15: =SUM(I6:I14) -> 0 | ... Q15: =SUM(Q6:Q14) -> 0
A17: TAKINGS
A18: 0.01
A19: 0.05
A20: 0.2
A21: 0.5
A22: 1
A23: 2
A24: 5
A25: 10
A26: 20
A27: Total | B27: =SUM(B18:B26) -> 0 | C27: =SUM(C18:C26) -> 0 | D27: =SUM(D18:D26) -> 0 | E27: =SUM(E18:E26) -> 0 | F27: =SUM(F18:F26) -> 0 | G27: =SUM(G18:G26) -> 0 | H27: =SUM(H18:H26) -> 0 | I27: =SUM(I18:I26) -> 0 | ... Q27: =SUM(Q18:Q26) -> 0
A29: SAFE
A30: 0.01
A31: 0.05
A32: 0.2
A33: 0.5
A34: 1
A35: 2
A36: 5
A37: 10
A38: 20
A39: Total | B39: =SUM(B35:B38) -> 0 | C39: =SUM(C35:C38) -> 0 | D39: =SUM(D35:D38) -> 0 | E39: =SUM(E35:E38) -> 0 | F39: =SUM(F35:F38) -> 0 | G39: =SUM(G35:G38) -> 0 | H39: =SUM(H35:H38) -> 0 | I39: =SUM(I35:I38) -> 0 | ... Q39: =SUM(Q35:Q38) -> 0
A41: RECEIPTS (Dockets Attached)
A42: Receipt 1
A43: Receipt 2
A44: Receipt 3
A45: Receipt 4
A46: Receipt 5
A47: Receipt 6
A48: Receipt 7
A49: Receipt 8
A50: Total | B50: =SUM(B42:B49) -> 0 | C50: =SUM(C42:C49) -> 0 | D50: =SUM(D42:D49) -> 0 | E50: =SUM(E42:E49) -> 0 | F50: =SUM(F42:F49) -> 0 | G50: =SUM(G42:G49) -> 0 | H50: =SUM(H42:H49) -> 0 | I50: =SUM(I42:I49) -> 0 | ... Q50: =SUM(Q42:Q49) -> 0
A52: ACCOUNTS
A53: Studio
A54: House Account
A55: Gift Cards
A56: Total | B56: =SUM(B51:B55) -> 0 | C56: =SUM(C51:C55) -> 0 | D56: =SUM(D51:D55) -> 0 | E56: =SUM(E51:E55) -> 0 | F56: =SUM(F51:F55) -> 0 | G56: =SUM(G51:G55) -> 0 | H56: =SUM(H51:H55) -> 0 | I56: =SUM(I51:I55) -> 0 | ... Q56: =SUM(Q51:Q55) -> 0
A58: SALES
A59: Coffee | B59: 3000 | C59: 4000 | D59: 5000
A60: Food
A61: Soft Drinks
A62: Alcohol
A63: Retail
A64: Room Hire
A65: Total | B65: =SUM(B59:B64) -> 3000 | C65: =SUM(C59:C64) -> 4000 | D65: =SUM(D59:D64) -> 5000 | E65: =SUM(E59:E64) -> 0 | F65: =SUM(F59:F64) -> 0 | G65: =SUM(G59:G64) -> 0 | H65: =SUM(H59:H64) -> 0 | I65: =SUM(I59:I64) -> 0 | ... Q65: =SUM(Q59:Q64) -> 0
A67: Cash Banked | B67: =B27 -> 0 | C67: =C27 -> 0 | D67: =D27 -> 0 | E67: =E27 -> 0 | F67: =F27 -> 0 | G67: =G27 -> 0 | H67: =H27 -> 0 | I67: =I27 -> 0 | ... Q67: =Q27 -> 0
A68: Z Read
A69: Accounts | B69: =B53 -> 0 | C69: =C53 -> 0 | D69: =D53 -> 0 | E69: =E53 -> 0 | F69: =F53 -> 0 | G69: =G53 -> 0 | H69: =H53 -> 0 | I69: =I53 -> 0 | ... Q69: =Q53 -> 0
A70: Receipts | B70: =B50 -> 0 | C70: =C50 -> 0 | D70: =D50 -> 0 | E70: =E50 -> 0 | F70: =F50 -> 0 | G70: =G50 -> 0 | H70: =H50 -> 0 | I70: =I50 -> 0 | ... Q70: =Q50 -> 0
A71: TOTAL | B71: =B67+B68-B69-B70 -> 0 | C71: =C67+C68-C69-C70 -> 0 | D71: =D67+D68-D69-D70 -> 0 | E71: =E67+E68-E69-E70 -> 0 | F71: =F67+F68-F69-F70 -> 0 | G71: =G67+G68-G69-G70 -> 0 | H71: =H67+H68-H69-H70 -> 0 | I71: =I67+I68-I69-I70 -> 0 | ... Q71: =Q67+Q68-Q69-Q70 -> 0
A73: Variance | B73: =B71-B65 -> -3000 | C73: =C71-C65 -> -4000 | D73: =D71-D65 -> -5000 | E73: =E71-E65 -> 0 | F73: =F71-F65 -> 0 | G73: =G71-G65 -> 0 | H73: =H71-H65 -> 0 | I73: =I71-I65 -> 0 | ... Q73: =Q71-Q65 -> 0
A76: TOTAL SALES
A77: TOTAL NET FOOD SALES
A78: TOTAL NET BEV SALES
A81: BANKED MONEY
A82: Cash Bag Number
A83: Cash Paying In Slip
A84: HSBC Receipt No
A85: Banking Manager
A86: Date

Sheet MON
A3: COMMENTS
A7: TILL FLOAT (No. of coins/notes) | B7: MONDAY
A8: 0.01
A9: 0.02
A10: 0.05
A11: 0.1
A12: 0.2
A13: 0.5
A14: 1
A15: 2
A16: 5
A17: 10
A18: 20
A19: Total | B19: =SUM((B8*A8),(B9*A9),(B10*A10),(B11*A11),(B12*A12),(B13*A13),(B14*A14),(B15*A15),(B16*A16),(B17*A17),(B18*A18)) -> 0
A20: TILL VARIANCE Should be 0! | B20: =500-B19 -> 500
A22: TAKINGS (No. of coins/notes) | B22: =B7 -> MONDAY
A23: 0.01
A24: 0.02
A25: 0.05
A26: 0.1
A27: 0.2
A28: 0.5
A29: 1
A30: 2
A31: 5
A32: 10
A33: 20
A34: Total | B34: =SUM((B23*A23),(B24*A24),(B25*A25),(B26*A26),(B27*A27),(B28*A28),(B29*A29),(B30*A30),(B31*A31),(B32*A32),(B33*A33)) -> 0
A36: SAFE (No. of coins/notes) | B36: =B7 -> MONDAY
A37: 0.01
A38: 0.02
A39: 0.05
A40: 0.1
A41: 0.2
A42: 0.5
A43: 1
A44: 2
A45: 5
A46: 10
A47: 20
A48: Total | B48: =SUM((B37*A37),(B38*A38),(B39*A39),(B40*A40),(B41*A41),(B42*A42),(B43*A43),(B44*A44),(B45*A45),(B46*A46),(B47*A47)) -> 0
A50: RECEIPTS Amount (Dockets Attached) | B50: =B7 -> MONDAY
A51: Receipt 1
A52: Receipt 2
A53: Receipt 3
A54: Receipt 4
A55: Receipt 5
A56: Receipt 6
A57: Receipt 7
A58: Receipt 8
A59: Total | B59: =SUM(B51:B58) -> 0
A61: ACCOUNTS | B61: =B7 -> MONDAY
A62: Studio Account Name | B62: Amount
A63: …
A64: Gift Cards
A65: Total | B65: =SUM(B63:B64) -> 0
A67: SALES | B67: =B7 -> MONDAY
A68: Coffee
A69: Food
A70: Soft Drinks
A71: Alcohol
A72: Retail
A73: Room Hire
A74: VAT | B74: =B75-SUM(B68:B73) -> 0
A75: Total
A77: Cash Banked | B77: =B34 -> 0
A78: Z Read 1
A79: Z Read 2
A80: Z Read 3
A81: Accounts | B81: =B65 -> 0
A82: Receipts | B82: =B59 -> 0
A83: TOTAL | B83: =B77+B78+B79+B80+B81+B82 -> 0
A85: Variance | B85: =B83-B75 -> 0
A88: BANKED MONEY | B88: =B7 -> MONDAY
A89: Cash Bag Number
A90: Cash Paying In Slip
A91: HSBC Receipt No
A92: Closing Supervisor
A93: Date
A95: DISCOUNTS/COMPS
A96: Comp 1
A97: Comp 2
A98: Comp 3
A99: Comp 4
A100: Comp 5
A101: Comp 6
... A105: Comp 10
A106: Total Comps | B106: =SUM(B96:B104) -> 0

Sheet TUES
A3: COMMENTS
A7: TILL FLOAT (No. of coins/notes) | B7: TUESDAY
A8: 0.01
A9: 0.02
A10: 0.05
A11: 0.1
A12: 0.2
A13: 0.5
A14: 1
A15: 2
A16: 5
A17: 10
A18: 20
A19: Total | B19: =SUM((B8*A8),(B9*A9),(B10*A10),(B11*A11),(B12*A12),(B13*A13),(B14*A14),(B15*A15),(B16*A16),(B17*A17),(B18*A18)) -> 0
A20: TILL VARIANCE Should be 0! | B20: =500-B19 -> 500
A22: TAKINGS (No. of coins/notes) | B22: =B7 -> TUESDAY
A23: 0.01
A24: 0.02
A25: 0.05
A26: 0.1
A27: 0.2
A28: 0.5
A29: 1
A30: 2
A31: 5
A32: 10
A33: 20
A34: Total | B34: =SUM((B23*A23),(B24*A24),(B25*A25),(B26*A26),(B27*A27),(B28*A28),(B29*A29),(B30*A30),(B31*A31),(B32*A32),(B33*A33)) -> 0
A36: SAFE (No. of coins/notes) | B36: =B7 -> TUESDAY
A37: 0.01
A38: 0.02
A39: 0.05
A40: 0.1
A41: 0.2
A42: 0.5
A43: 1
A44: 2
A45: 5
A46: 10
A47: 20
A48: Total | B48: =SUM((B37*A37),(B38*A38),(B39*A39),(B40*A40),(B41*A41),(B42*A42),(B43*A43),(B44*A44),(B45*A45),(B46*A46),(B47*A47)) -> 0
A50: RECEIPTS Amount (Dockets Attached) | B50: =B7 -> TUESDAY
A51: Receipt 1
A52: Receipt 2
A53: Receipt 3
A54: Receipt 4
A55: Receipt 5
A56: Receipt 6
A57: Receipt 7
A58: Receipt 8
A59: Total | B59: =SUM(B51:B58) -> 0
A61: ACCOUNTS | B61: =B7 -> TUESDAY
A62: Studio Account Name | B62: Amount
A63: …
A64: Gift Cards
A65: Total | B65: =SUM(B63:B64) -> 0
A67: SALES | B67: =B7 -> TUESDAY
A68: Coffee
A69: Food
A70: Soft Drinks
A71: Alcohol
A72: Retail
A73: Room Hire
A74: VAT | B74: =B75-SUM(B68:B73) -> 0
A75: Total
A77: Cash Banked | B77: =B34 -> 0
A78: Z Read 1
A79: Z Read 2
A80: Z Read 3
A81: Accounts | B81: =B65 -> 0
A82: Receipts | B82: =B59 -> 0
A83: TOTAL | B83: =B77+B78+B79+B80+B81+B82 -> 0
A85: Variance | B85: =B83-B75 -> 0
A88: BANKED MONEY | B88: =B7 -> TUESDAY
A89: Cash Bag Number
A90: Cash Paying In Slip
A91: HSBC Receipt No
A92: Closing Supervisor
A93: Date
A95: DISCOUNTS/COMPS
A96: Comp 1
A97: Comp 2
A98: Comp 3
A99: Comp 4
A100: Comp 5
A101: Comp 6
... A105: Comp 10
A106: Total Comps | B106: =SUM(B96:B104) -> 0

Sheet WED
A3: COMMENTS
A7: TILL FLOAT (No. of coins/notes) | B7: WEDNESDAY
A8: 0.01
A9: 0.02
A10: 0.05
A11: 0.1
A12: 0.2
A13: 0.5
A14: 1
A15: 2
A16: 5
A17: 10
A18: 20
A19: Total | B19: =SUM((B8*A8),(B9*A9),(B10*A10),(B11*A11),(B12*A12),(B13*A13),(B14*A14),(B15*A15),(B16*A16),(B17*A17),(B18*A18)) -> 0
A20: TILL VARIANCE Should be 0! | B20: =500-B19 -> 500
A22: TAKINGS (No. of coins/notes) | B22: =B7 -> WEDNESDAY
A23: 0.01
A24: 0.02
A25: 0.05
A26: 0.1
A27: 0.2
A28: 0.5
A29: 1
A30: 2
A31: 5
A32: 10
A33: 20
A34: Total | B34: =SUM((B23*A23),(B24*A24),(B25*A25),(B26*A26),(B27*A27),(B28*A28),(B29*A29),(B30*A30),(B31*A31),(B32*A32),(B33*A33)) -> 0
A36: SAFE (No. of coins/notes) | B36: =B7 -> WEDNESDAY
A37: 0.01
A38: 0.02
A39: 0.05
A40: 0.1
A41: 0.2
A42: 0.5
A43: 1
A44: 2
A45: 5
A46: 10
A47: 20
A48: Total | B48: =SUM((B37*A37),(B38*A38),(B39*A39),(B40*A40),(B41*A41),(B42*A42),(B43*A43),(B44*A44),(B45*A45),(B46*A46),(B47*A47)) -> 0
A50: RECEIPTS Amount (Dockets Attached) | B50: =B7 -> WEDNESDAY
A51: Receipt 1
A52: Receipt 2
A53: Receipt 3
A54: Receipt 4
A55: Receipt 5
A56: Receipt 6
A57: Receipt 7
A58: Receipt 8
A59: Total | B59: =SUM(B51:B58) -> 0
A61: ACCOUNTS | B61: =B7 -> WEDNESDAY
A62: Studio Account Name | B62: Amount
A63: …
A64: Gift Cards
A65: Total | B65: =SUM(B63:B64) -> 0
A67: SALES | B67: =B7 -> WEDNESDAY
A68: Coffee
A69: Food
A70: Soft Drinks
A71: Alcohol
A72: Retail
A73: Room Hire
A74: VAT | B74: =B75-SUM(B68:B73) -> 0
A75: Total
A77: Cash Banked | B77: =B34 -> 0
A78: Z Read 1
A79: Z Read 2
A80: Z Read 3
A81: Accounts | B81: =B65 -> 0
A82: Receipts | B82: =B59 -> 0
A83: TOTAL | B83: =B77+B78+B79+B80+B81+B82 -> 0
A85: Variance | B85: =B83-B75 -> 0
A88: BANKED MONEY | B88: =B7 -> WEDNESDAY
A89: Cash Bag Number
A90: Cash Paying In Slip
A91: HSBC Receipt No
A92: Closing Supervisor
A93: Date
A95: DISCOUNTS/COMPS
A96: Comp 1
A97: Comp 2
A98: Comp 3
A99: Comp 4
A100: Comp 5
A101: Comp 6
... A105: Comp 10
A106: Total Comps | B106: =SUM(B96:B104) -> 0

Sheet THUR
A3: COMMENTS
A7: TILL FLOAT (No. of coins/notes) | B7: THURSDAY
A8: 0.01
A9: 0.02
A10: 0.05
A11: 0.1
A12: 0.2
A13: 0.5
A14: 1
A15: 2
A16: 5
A17: 10
A18: 20
A19: Total | B19: =SUM((B8*A8),(B9*A9),(B10*A10),(B11*A11),(B12*A12),(B13*A13),(B14*A14),(B15*A15),(B16*A16),(B17*A17),(B18*A18)) -> 0
A20: TILL VARIANCE Should be 0! | B20: =500-B19 -> 500
A22: TAKINGS (No. of coins/notes) | B22: =B7 -> THURSDAY
A23: 0.01
A24: 0.02
A25: 0.05
A26: 0.1
A27: 0.2
A28: 0.5
A29: 1
A30: 2
A31: 5
A32: 10
A33: 20
A34: Total | B34: =SUM((B23*A23),(B24*A24),(B25*A25),(B26*A26),(B27*A27),(B28*A28),(B29*A29),(B30*A30),(B31*A31),(B32*A32),(B33*A33)) -> 0
A36: SAFE (No. of coins/notes) | B36: =B7 -> THURSDAY
A37: 0.01
A38: 0.02
A39: 0.05
A40: 0.1
A41: 0.2
A42: 0.5
A43: 1
A44: 2
A45: 5
A46: 10
A47: 20
A48: Total | B48: =SUM((B37*A37),(B38*A38),(B39*A39),(B40*A40),(B41*A41),(B42*A42),(B43*A43),(B44*A44),(B45*A45),(B46*A46),(B47*A47)) -> 0
A50: RECEIPTS Amount (Dockets Attached) | B50: =B7 -> THURSDAY
A51: Receipt 1
A52: Receipt 2
A53: Receipt 3
A54: Receipt 4
A55: Receipt 5
A56: Receipt 6
A57: Receipt 7
A58: Receipt 8
A59: Total | B59: =SUM(B51:B58) -> 0
A61: ACCOUNTS | B61: =B7 -> THURSDAY
A62: Studio Account Name | B62: Amount
A63: …
A64: Gift Cards
A65: Total | B65: =SUM(B63:B64) -> 0
A67: SALES | B67: =B7 -> THURSDAY
A68: Coffee
A69: Food
A70: Soft Drinks
A71: Alcohol
A72: Retail
A73: Room Hire
A74: VAT | B74: =B75-SUM(B68:B73) -> 0
A75: Total
A77: Cash Banked | B77: =B34 -> 0
A78: Z Read 1
A79: Z Read 2
A80: Z Read 3
A81: Accounts | B81: =B65 -> 0
A82: Receipts | B82: =B59 -> 0
A83: TOTAL | B83: =B77+B78+B79+B80+B81+B82 -> 0
A85: Variance | B85: =B83-B75 -> 0
A88: BANKED MONEY | B88: =B7 -> THURSDAY
A89: Cash Bag Number
A90: Cash Paying In Slip
A91: HSBC Receipt No
A92: Closing Supervisor
A93: Date
A95: DISCOUNTS/COMPS
A96: Comp 1
A97: Comp 2
A98: Comp 3
A99: Comp 4
A100: Comp 5
A101: Comp 6
... A105: Comp 10
A106: Total Comps | B106: =SUM(B96:B104) -> 0

Sheet FRI
A3: COMMENTS
A7: TILL FLOAT (No. of coins/notes) | B7: FRIDAY
A8: 0.01
A9: 0.02
A10: 0.05
A11: 0.1
A12: 0.2
A13: 0.5
A14: 1
A15: 2
A16: 5
A17: 10
A18: 20
A19: Total | B19: =SUM((B8*A8),(B9*A9),(B10*A10),(B11*A11),(B12*A12),(B13*A13),(B14*A14),(B15*A15),(B16*A16),(B17*A17),(B18*A18)) -> 0
A20: TILL VARIANCE Should be 0! | B20: =500-B19 -> 500
A22: TAKINGS (No. of coins/notes) | B22: =B7 -> FRIDAY
A23: 0.01
A24: 0.02
A25: 0.05
A26: 0.1
A27: 0.2
A28: 0.5
A29: 1
A30: 2
A31: 5
A32: 10
A33: 20
A34: Total | B34: =SUM((B23*A23),(B24*A24),(B25*A25),(B26*A26),(B27*A27),(B28*A28),(B29*A29),(B30*A30),(B31*A31),(B32*A32),(B33*A33)) -> 0
A36: SAFE (No. of coins/notes) | B36: =B7 -> FRIDAY
A37: 0.01
A38: 0.02
A39: 0.05
A40: 0.1
A41: 0.2
A42: 0.5
A43: 1
A44: 2
A45: 5
A46: 10
A47: 20
A48: Total | B48: =SUM((B37*A37),(B38*A38),(B39*A39),(B40*A40),(B41*A41),(B42*A42),(B43*A43),(B44*A44),(B45*A45),(B46*A46),(B47*A47)) -> 0
A50: RECEIPTS Amount (Dockets Attached) | B50: =B7 -> FRIDAY
A51: Receipt 1
A52: Receipt 2
A53: Receipt 3
A54: Receipt 4
A55: Receipt 5
A56: Receipt 6
A57: Receipt 7
A58: Receipt 8
A59: Total | B59: =SUM(B51:B58) -> 0
A61: ACCOUNTS | B61: =B7 -> FRIDAY
A62: Studio Account Name | B62: Amount
A63: …
A64: Gift Cards
A65: Total | B65: =SUM(B63:B64) -> 0
A67: SALES | B67: =B7 -> FRIDAY
A68: Coffee
A69: Food
A70: Soft Drinks
A71: Alcohol
A72: Retail
A73: Room Hire
A74: VAT | B74: =B75-SUM(B68:B73) -> 0
A75: Total
A77: Cash Banked | B77: =B34 -> 0
A78: Z Read 1
A79: Z Read 2
A80: Z Read 3
A81: Accounts | B81: =B65 -> 0
A82: Receipts | B82: =B59 -> 0
A83: TOTAL | B83: =B77+B78+B79+B80+B81+B82 -> 0
A85: Variance | B85: =B83-B75 -> 0
A88: BANKED MONEY | B88: =B7 -> FRIDAY
A89: Cash Bag Number
A90: Cash Paying In Slip
A91: HSBC Receipt No
A92: Closing Supervisor
A93: Date
A95: DISCOUNTS/COMPS
A96: Comp 1
A97: Comp 2
A98: Comp 3
A99: Comp 4
A100: Comp 5
A101: Comp 6
... A105: Comp 10
A106: Total Comps | B106: =SUM(B96:B104) -> 0

Sheet SAT
A3: COMMENTS
A7: TILL FLOAT (No. of coins/notes) | B7: SATURDAY
A8: 0.01
A9: 0.02
A10: 0.05
A11: 0.1
A12: 0.2
A13: 0.5
A14: 1
A15: 2
A16: 5
A17: 10
A18: 20
A19: Total | B19: =SUM((B8*A8),(B9*A9),(B10*A10),(B11*A11),(B12*A12),(B13*A13),(B14*A14),(B15*A15),(B16*A16),(B17*A17),(B18*A18)) -> 0
A20: TILL VARIANCE Should be 0! | B20: =500-B19 -> 500
A22: TAKINGS (No. of coins/notes) | B22: =B7 -> SATURDAY
A23: 0.01
A24: 0.02
A25: 0.05
A26: 0.1
A27: 0.2
A28: 0.5
A29: 1
A30: 2
A31: 5
A32: 10
A33: 20
A34: Total | B34: =SUM((B23*A23),(B24*A24),(B25*A25),(B26*A26),(B27*A27),(B28*A28),(B29*A29),(B30*A30),(B31*A31),(B32*A32),(B33*A33)) -> 0
A36: SAFE (No. of coins/notes) | B36: =B7 -> SATURDAY
A37: 0.01
A38: 0.02
A39: 0.05
A40: 0.1
A41: 0.2
A42: 0.5
A43: 1
A44: 2
A45: 5
A46: 10
A47: 20
A48: Total | B48: =SUM((B37*A37),(B38*A38),(B39*A39),(B40*A40),(B41*A41),(B42*A42),(B43*A43),(B44*A44),(B45*A45),(B46*A46),(B47*A47)) -> 0
A50: RECEIPTS Amount (Dockets Attached) | B50: =B7 -> SATURDAY
A51: Receipt 1
A52: Receipt 2
A53: Receipt 3
A54: Receipt 4
A55: Receipt 5
A56: Receipt 6
A57: Receipt 7
A58: Receipt 8
A59: Total | B59: =SUM(B51:B58) -> 0
A61: ACCOUNTS | B61: =B7 -> SATURDAY
A62: Studio Account Name | B62: Amount
A63: …
A64: Gift Cards
A65: Total | B65: =SUM(B63:B64) -> 0
A67: SALES | B67: =B7 -> SATURDAY
A68: Coffee
A69: Food
A70: Soft Drinks
A71: Alcohol
A72: Retail
A73: Room Hire
A74: VAT | B74: =B75-SUM(B68:B73) -> 0
A75: Total
A77: Cash Banked | B77: =B34 -> 0
A78: Z Read 1
A79: Z Read 2
A80: Z Read 3
A81: Accounts | B81: =B65 -> 0
A82: Receipts | B82: =B59 -> 0
A83: TOTAL | B83: =B77+B78+B79+B80+B81+B82 -> 0
A85: Variance | B85: =B83-B75 -> 0
A88: BANKED MONEY | B88: =B7 -> SATURDAY
A89: Cash Bag Number
A90: Cash Paying In Slip
A91: HSBC Receipt No
A92: Closing Supervisor
A93: Date
A95: DISCOUNTS/COMPS
A96: Comp 1
A97: Comp 2
A98: Comp 3
A99: Comp 4
A100: Comp 5
A101: Comp 6
... A105: Comp 10
A106: Total Comps | B106: =SUM(B96:B104) -> 0

Sheet SUN
A3: COMMENTS
A7: TILL FLOAT (No. of coins/notes) | B7: SUNDAY
A8: 0.01
A9: 0.02
A10: 0.05
A11: 0.1
A12: 0.2
A13: 0.5
A14: 1
A15: 2
A16: 5
A17: 10
A18: 20
A19: Total | B19: =SUM((B8*A8),(B9*A9),(B10*A10),(B11*A11),(B12*A12),(B13*A13),(B14*A14),(B15*A15),(B16*A16),(B17*A17),(B18*A18)) -> 0
A20: TILL VARIANCE Should be 0! | B20: =500-B19 -> 500
A22: TAKINGS (No. of coins/notes) | B22: =B7 -> SUNDAY
A23: 0.01
A24: 0.02
A25: 0.05
A26: 0.1
A27: 0.2
A28: 0.5
A29: 1
A30: 2
A31: 5
A32: 10
A33: 20
A34: Total | B34: =SUM((B23*A23),(B24*A24),(B25*A25),(B26*A26),(B27*A27),(B28*A28),(B29*A29),(B30*A30),(B31*A31),(B32*A32),(B33*A33)) -> 0
A36: SAFE (No. of coins/notes) | B36: =B7 -> SUNDAY
A37: 0.01
A38: 0.02
A39: 0.05
A40: 0.1
A41: 0.2
A42: 0.5
A43: 1
A44: 2
A45: 5
A46: 10
A47: 20
A48: Total | B48: =SUM((B37*A37),(B38*A38),(B39*A39),(B40*A40),(B41*A41),(B42*A42),(B43*A43),(B44*A44),(B45*A45),(B46*A46),(B47*A47)) -> 0
A50: RECEIPTS Amount (Dockets Attached) | B50: =B7 -> SUNDAY
A51: Receipt 1
A52: Receipt 2
A53: Receipt 3
A54: Receipt 4
A55: Receipt 5
A56: Receipt 6
A57: Receipt 7
A58: Receipt 8
A59: Total | B59: =SUM(B51:B58) -> 0
A61: ACCOUNTS | B61: =B7 -> SUNDAY
A62: Studio Account Name | B62: Amount
A63: …
A64: Gift Cards
A65: Total | B65: =SUM(B63:B64) -> 0
A67: SALES | B67: =B7 -> SUNDAY
A68: Coffee
A69: Food
A70: Soft Drinks
A71: Alcohol
A72: Retail
A73: Room Hire
A74: VAT | B74: =B75-SUM(B68:B73) -> 0
A75: Total
A77: Cash Banked | B77: =B34 -> 0
A78: Z Read 1
A79: Z Read 2
A80: Z Read 3
A81: Accounts | B81: =B65 -> 0
A82: Receipts | B82: =B59 -> 0
A83: TOTAL | B83: =B77+B78+B79+B80+B81+B82 -> 0
A85: Variance | B85: =B83-B75 -> 0
A88: BANKED MONEY | B88: =B7 -> SUNDAY
A89: Cash Bag Number
A90: Cash Paying In Slip
A91: HSBC Receipt No
A92: Closing Supervisor
A93: Date
A95: DISCOUNTS/COMPS
A96: Comp 1
A97: Comp 2
A98: Comp 3
A99: Comp 4
A100: Comp 5
A101: Comp 6
... A105: Comp 10
A106: Total Comps | B106: =SUM(B96:B104) -> 0

Sheet WEEKBEGDATE
A3: =MON!A7 -> TILL FLOAT (No. of coins/notes) | B3: =MON!B7 -> MONDAY | C3: =TUES!B7 -> TUESDAY | D3: =WED!B7 -> WEDNESDAY | E3: =THUR!B7 -> THURSDAY | F3: =FRI!B7 -> FRIDAY | G3: =SAT!B7 -> SATURDAY | H3: =SUN!B7 -> SUNDAY | I3: TOTAL
A4: =MON!A8 -> 0.01 | B4: =MON!B8 -> 0 | C4: =TUES!B8 -> 0 | D4: =WED!B8 -> 0 | E4: =THUR!B8 -> 0 | F4: =FRI!B8 -> 0 | G4: =SAT!B8 -> 0 | H4: =SUN!B8 -> 0 | I4: =SUM(B4:H4) -> 0
A5: =MON!A9 -> 0.02 | B5: =MON!B9 -> 0 | C5: =TUES!B9 -> 0 | D5: =WED!B9 -> 0 | E5: =THUR!B9 -> 0 | F5: =FRI!B9 -> 0 | G5: =SAT!B9 -> 0 | H5: =SUN!B9 -> 0 | I5: =SUM(B5:H5) -> 0
A6: =MON!A10 -> 0.05 | B6: =MON!B10 -> 0 | C6: =TUES!B10 -> 0 | D6: =WED!B10 -> 0 | E6: =THUR!B10 -> 0 | F6: =FRI!B10 -> 0 | G6: =SAT!B10 -> 0 | H6: =SUN!B10 -> 0 | I6: =SUM(B6:H6) -> 0
A7: =MON!A11 -> 0.1 | B7: =MON!B11 -> 0 | C7: =TUES!B11 -> 0 | D7: =WED!B11 -> 0 | E7: =THUR!B11 -> 0 | F7: =FRI!B11 -> 0 | G7: =SAT!B11 -> 0 | H7: =SUN!B11 -> 0 | I7: =SUM(B7:H7) -> 0
A8: =MON!A12 -> 0.2 | B8: =MON!B12 -> 0 | C8: =TUES!B12 -> 0 | D8: =WED!B12 -> 0 | E8: =THUR!B12 -> 0 | F8: =FRI!B12 -> 0 | G8: =SAT!B12 -> 0 | H8: =SUN!B12 -> 0 | I8: =SUM(B8:H8) -> 0
A9: =MON!A13 -> 0.5 | B9: =MON!B13 -> 0 | C9: =TUES!B13 -> 0 | D9: =WED!B13 -> 0 | E9: =THUR!B13 -> 0 | F9: =FRI!B13 -> 0 | G9: =SAT!B13 -> 0 | H9: =SUN!B13 -> 0 | I9: =SUM(B9:H9) -> 0
A10: =MON!A14 -> 1 | B10: =MON!B14 -> 0 | C10: =TUES!B14 -> 0 | D10: =WED!B14 -> 0 | E10: =THUR!B14 -> 0 | F10: =FRI!B14 -> 0 | G10: =SAT!B14 -> 0 | H10: =SUN!B14 -> 0 | I10: =SUM(B10:H10) -> 0
A11: =MON!A15 -> 2 | B11: =MON!B15 -> 0 | C11: =TUES!B15 -> 0 | D11: =WED!B15 -> 0 | E11: =THUR!B15 -> 0 | F11: =FRI!B15 -> 0 | G11: =SAT!B15 -> 0 | H11: =SUN!B15 -> 0 | I11: =SUM(B11:H11) -> 0
A12: =MON!A16 -> 5 | B12: =MON!B16 -> 0 | C12: =TUES!B16 -> 0 | D12: =WED!B16 -> 0 | E12: =THUR!B16 -> 0 | F12: =FRI!B16 -> 0 | G12: =SAT!B16 -> 0 | H12: =SUN!B16 -> 0 | I12: =SUM(B12:H12) -> 0
A13: =MON!A17 -> 10 | B13: =MON!B17 -> 0 | C13: =TUES!B17 -> 0 | D13: =WED!B17 -> 0 | E13: =THUR!B17 -> 0 | F13: =FRI!B17 -> 0 | G13: =SAT!B17 -> 0 | H13: =SUN!B17 -> 0 | I13: =SUM(B13:H13) -> 0
A14: =MON!A18 -> 20 | B14: =MON!B18 -> 0 | C14: =TUES!B18 -> 0 | D14: =WED!B18 -> 0 | E14: =THUR!B18 -> 0 | F14: =FRI!B18 -> 0 | G14: =SAT!B18 -> 0 | H14: =SUN!B18 -> 0 | I14: =SUM(B14:H14) -> 0
A15: =MON!A19 -> Total | B15: =MON!B19 -> 0 | C15: =TUES!B19 -> 0 | D15: =WED!B19 -> 0 | E15: =THUR!B19 -> 0 | F15: =FRI!B19 -> 0 | G15: =SAT!B19 -> 0 | H15: =SUN!B19 -> 0 | I15: =SUM(I4:I14) -> 0
A16: =IF(I16>10,"THIS SHOULD BE ZERO","") -> THIS SHOULD BE ZERO | B16: =MON!B20 -> 500 | C16: =TUES!B20 -> 500 | D16: =WED!B20 -> 500 | E16: =THUR!B20 -> 500 | F16: =FRI!B20 -> 500 | G16: =SAT!B20 -> 500 | H16: =SUN!B20 -> 500 | I16: =SUM(B16:H16) -> 3500
A18: =MON!A22 -> TAKINGS (No. of coins/notes) | B18: =MON!B22 -> MONDAY | C18: =TUES!B22 -> TUESDAY | D18: =WED!B22 -> WEDNESDAY | E18: =THUR!B22 -> THURSDAY | F18: =FRI!B22 -> FRIDAY | G18: =SAT!B22 -> SATURDAY | H18: =SUN!B22 -> SUNDAY | I18: =I3 -> TOTAL
A19: =MON!A23 -> 0.01 | B19: =MON!B23 -> 0 | C19: =TUES!B23 -> 0 | D19: =WED!B23 -> 0 | E19: =THUR!B23 -> 0 | F19: =FRI!B23 -> 0 | G19: =SAT!B23 -> 0 | H19: =SUN!B23 -> 0 | I19: =SUM(B19:H19) -> 0
A20: =MON!A24 -> 0.02 | B20: =MON!B24 -> 0 | C20: =TUES!B24 -> 0 | D20: =WED!B24 -> 0 | E20: =THUR!B24 -> 0 | F20: =FRI!B24 -> 0 | G20: =SAT!B24 -> 0 | H20: =SUN!B24 -> 0 | I20: =SUM(B20:H20) -> 0
A21: =MON!A25 -> 0.05 | B21: =MON!B25 -> 0 | C21: =TUES!B25 -> 0 | D21: =WED!B25 -> 0 | E21: =THUR!B25 -> 0 | F21: =FRI!B25 -> 0 | G21: =SAT!B25 -> 0 | H21: =SUN!B25 -> 0 | I21: =SUM(B21:H21) -> 0
A22: =MON!A26 -> 0.1 | B22: =MON!B26 -> 0 | C22: =TUES!B26 -> 0 | D22: =WED!B26 -> 0 | E22: =THUR!B26 -> 0 | F22: =FRI!B26 -> 0 | G22: =SAT!B26 -> 0 | H22: =SUN!B26 -> 0 | I22: =SUM(B22:H22) -> 0
A23: =MON!A27 -> 0.2 | B23: =MON!B27 -> 0 | C23: =TUES!B27 -> 0 | D23: =WED!B27 -> 0 | E23: =THUR!B27 -> 0 | F23: =FRI!B27 -> 0 | G23: =SAT!B27 -> 0 | H23: =SUN!B27 -> 0 | I23: =SUM(B23:H23) -> 0
A24: =MON!A28 -> 0.5 | B24: =MON!B28 -> 0 | C24: =TUES!B28 -> 0 | D24: =WED!B28 -> 0 | E24: =THUR!B28 -> 0 | F24: =FRI!B28 -> 0 | G24: =SAT!B28 -> 0 | H24: =SUN!B28 -> 0 | I24: =SUM(B24:H24) -> 0
A25: =MON!A29 -> 1 | B25: =MON!B29 -> 0 | C25: =TUES!B29 -> 0 | D25: =WED!B29 -> 0 | E25: =THUR!B29 -> 0 | F25: =FRI!B29 -> 0 | G25: =SAT!B29 -> 0 | H25: =SUN!B29 -> 0 | I25: =SUM(B25:H25) -> 0
A26: =MON!A30 -> 2 | B26: =MON!B30 -> 0 | C26: =TUES!B30 -> 0 | D26: =WED!B30 -> 0 | E26: =THUR!B30 -> 0 | F26: =FRI!B30 -> 0 | G26: =SAT!B30 -> 0 | H26: =SUN!B30 -> 0 | I26: =SUM(B26:H26) -> 0
A27: =MON!A31 -> 5 | B27: =MON!B31 -> 0 | C27: =TUES!B31 -> 0 | D27: =WED!B31 -> 0 | E27: =THUR!B31 -> 0 | F27: =FRI!B31 -> 0 | G27: =SAT!B31 -> 0 | H27: =SUN!B31 -> 0 | I27: =SUM(B27:H27) -> 0
A28: =MON!A32 -> 10 | B28: =MON!B32 -> 0 | C28: =TUES!B32 -> 0 | D28: =WED!B32 -> 0 | E28: =THUR!B32 -> 0 | F28: =FRI!B32 -> 0 | G28: =SAT!B32 -> 0 | H28: =SUN!B32 -> 0 | I28: =SUM(B28:H28) -> 0
A29: =MON!A33 -> 20 | B29: =MON!B33 -> 0 | C29: =TUES!B33 -> 0 | D29: =WED!B33 -> 0 | E29: =THUR!B33 -> 0 | F29: =FRI!B33 -> 0 | G29: =SAT!B33 -> 0 | H29: =SUN!B33 -> 0 | I29: =SUM(B29:H29) -> 0
A30: =MON!A34 -> Total | B30: =MON!B34 -> 0 | C30: =TUES!B34 -> 0 | D30: =WED!B34 -> 0 | E30: =THUR!B34 -> 0 | F30: =FRI!B34 -> 0 | G30: =SAT!B34 -> 0 | H30: =SUN!B34 -> 0 | I30: =SUM(I19:I29) -> 0
A32: =MON!A36 -> SAFE (No. of coins/notes) | B32: =MON!B36 -> MONDAY | C32: =TUES!B36 -> TUESDAY | D32: =WED!B36 -> WEDNESDAY | E32: =THUR!B36 -> THURSDAY | F32: =FRI!B36 -> FRIDAY | G32: =SAT!B36 -> SATURDAY | H32: =SUN!B36 -> SUNDAY | I32: =I3 -> TOTAL
A33: =MON!A37 -> 0.01 | B33: =MON!B37 -> 0 | C33: =TUES!B37 -> 0 | D33: =WED!B37 -> 0 | E33: =THUR!B37 -> 0 | F33: =FRI!B37 -> 0 | G33: =SAT!B37 -> 0 | H33: =SUN!B37 -> 0 | I33: =SUM(B33:H33) -> 0
A34: =MON!A38 -> 0.02 | B34: =MON!B38 -> 0 | C34: =TUES!B38 -> 0 | D34: =WED!B38 -> 0 | E34: =THUR!B38 -> 0 | F34: =FRI!B38 -> 0 | G34: =SAT!B38 -> 0 | H34: =SUN!B38 -> 0 | I34: =SUM(B34:H34) -> 0
A35: =MON!A39 -> 0.05 | B35: =MON!B39 -> 0 | C35: =TUES!B39 -> 0 | D35: =WED!B39 -> 0 | E35: =THUR!B39 -> 0 | F35: =FRI!B39 -> 0 | G35: =SAT!B39 -> 0 | H35: =SUN!B39 -> 0 | I35: =SUM(B35:H35) -> 0
A36: =MON!A40 -> 0.1 | B36: =MON!B40 -> 0 | C36: =TUES!B40 -> 0 | D36: =WED!B40 -> 0 | E36: =THUR!B40 -> 0 | F36: =FRI!B40 -> 0 | G36: =SAT!B40 -> 0 | H36: =SUN!B40 -> 0 | I36: =SUM(B36:H36) -> 0
A37: =MON!A41 -> 0.2 | B37: =MON!B41 -> 0 | C37: =TUES!B41 -> 0 | D37: =WED!B41 -> 0 | E37: =THUR!B41 -> 0 | F37: =FRI!B41 -> 0 | G37: =SAT!B41 -> 0 | H37: =SUN!B41 -> 0 | I37: =SUM(B37:H37) -> 0
A38: =MON!A42 -> 0.5 | B38: =MON!B42 -> 0 | C38: =TUES!B42 -> 0 | D38: =WED!B42 -> 0 | E38: =THUR!B42 -> 0 | F38: =FRI!B42 -> 0 | G38: =SAT!B42 -> 0 | H38: =SUN!B42 -> 0 | I38: =SUM(B38:H38) -> 0
A39: =MON!A43 -> 1 | B39: =MON!B43 -> 0 | C39: =TUES!B43 -> 0 | D39: =WED!B43 -> 0 | E39: =THUR!B43 -> 0 | F39: =FRI!B43 -> 0 | G39: =SAT!B43 -> 0 | H39: =SUN!B43 -> 0 | I39: =SUM(B39:H39) -> 0
A40: =MON!A44 -> 2 | B40: =MON!B44 -> 0 | C40: =TUES!B44 -> 0 | D40: =WED!B44 -> 0 | E40: =THUR!B44 -> 0 | F40: =FRI!B44 -> 0 | G40: =SAT!B44 -> 0 | H40: =SUN!B44 -> 0 | I40: =SUM(B40:H40) -> 0
A41: =MON!A45 -> 5 | B41: =MON!B45 -> 0 | C41: =TUES!B45 -> 0 | D41: =WED!B45 -> 0 | E41: =THUR!B45 -> 0 | F41: =FRI!B45 -> 0 | G41: =SAT!B45 -> 0 | H41: =SUN!B45 -> 0 | I41: =SUM(B41:H41) -> 0
A42: =MON!A46 -> 10 | B42: =MON!B46 -> 0 | C42: =TUES!B46 -> 0 | D42: =WED!B46 -> 0 | E42: =THUR!B46 -> 0 | F42: =FRI!B46 -> 0 | G42: =SAT!B46 -> 0 | H42: =SUN!B46 -> 0 | I42: =SUM(B42:H42) -> 0
A43: =MON!A47 -> 20 | B43: =MON!B47 -> 0 | C43: =TUES!B47 -> 0 | D43: =WED!B47 -> 0 | E43: =THUR!B47 -> 0 | F43: =FRI!B47 -> 0 | G43: =SAT!B47 -> 0 | H43: =SUN!B47 -> 0 | I43: =SUM(B43:H43) -> 0
A44: =MON!A48 -> Total | B44: =MON!B48 -> 0 | C44: =TUES!B48 -> 0 | D44: =WED!B48 -> 0 | E44: =THUR!B48 -> 0 | F44: =FRI!B48 -> 0 | G44: =SAT!B48 -> 0 | H44: =SUN!B48 -> 0 | I44: =SUM(I33:I43) -> 0
A46: =MON!A50 -> RECEIPTS Amount (Dockets Attached) | B46: =MON!B50 -> MONDAY | C46: =TUES!B50 -> TUESDAY | D46: =WED!B50 -> WEDNESDAY | E46: =THUR!B50 -> THURSDAY | F46: =FRI!B50 -> FRIDAY | G46: =SAT!B50 -> SATURDAY | H46: =SUN!B50 -> SUNDAY | I46: =I3 -> TOTAL
A47: =MON!A51 -> Receipt 1 | B47: =MON!B51 -> 0 | C47: =TUES!B51 -> 0 | D47: =WED!B51 -> 0 | E47: =THUR!B51 -> 0 | F47: =FRI!B51 -> 0 | G47: =SAT!B51 -> 0 | H47: =SUN!B51 -> 0 | I47: =SUM(B47:H47) -> 0
A48: =MON!A52 -> Receipt 2 | B48: =MON!B52 -> 0 | C48: =TUES!B52 -> 0 | D48: =WED!B52 -> 0 | E48: =THUR!B52 -> 0 | F48: =FRI!B52 -> 0 | G48: =SAT!B52 -> 0 | H48: =SUN!B52 -> 0 | I48: =SUM(B48:H48) -> 0
A49: =MON!A53 -> Receipt 3 | B49: =MON!B53 -> 0 | C49: =TUES!B53 -> 0 | D49: =WED!B53 -> 0 | E49: =THUR!B53 -> 0 | F49: =FRI!B53 -> 0 | G49: =SAT!B53 -> 0 | H49: =SUN!B53 -> 0 | I49: =SUM(B49:H49) -> 0
A50: =MON!A54 -> Receipt 4 | B50: =MON!B54 -> 0 | C50: =TUES!B54 -> 0 | D50: =WED!B54 -> 0 | E50: =THUR!B54 -> 0 | F50: =FRI!B54 -> 0 | G50: =SAT!B54 -> 0 | H50: =SUN!B54 -> 0 | I50: =SUM(B50:H50) -> 0
A51: =MON!A55 -> Receipt 5 | B51: =MON!B55 -> 0 | C51: =TUES!B55 -> 0 | D51: =WED!B55 -> 0 | E51: =THUR!B55 -> 0 | F51: =FRI!B55 -> 0 | G51: =SAT!B55 -> 0 | H51: =SUN!B55 -> 0 | I51: =SUM(B51:H51) -> 0
A52: =MON!A56 -> Receipt 6 | B52: =MON!B56 -> 0 | C52: =TUES!B56 -> 0 | D52: =WED!B56 -> 0 | E52: =THUR!B56 -> 0 | F52: =FRI!B56 -> 0 | G52: =SAT!B56 -> 0 | H52: =SUN!B56 -> 0 | I52: =SUM(B52:H52) -> 0
A53: =MON!A57 -> Receipt 7 | B53: =MON!B57 -> 0 | C53: =TUES!B57 -> 0 | D53: =WED!B57 -> 0 | E53: =THUR!B57 -> 0 | F53: =FRI!B57 -> 0 | G53: =SAT!B57 -> 0 | H53: =SUN!B57 -> 0 | I53: =SUM(B53:H53) -> 0
A54: =MON!A58 -> Receipt 8 | B54: =MON!B58 -> 0 | C54: =TUES!B58 -> 0 | D54: =WED!B58 -> 0 | E54: =THUR!B58 -> 0 | F54: =FRI!B58 -> 0 | G54: =SAT!B58 -> 0 | H54: =SUN!B58 -> 0 | I54: =SUM(B54:H54) -> 0
A55: =MON!A59 -> Total | B55: =MON!B59 -> 0 | C55: =TUES!B59 -> 0 | D55: =WED!B59 -> 0 | E55: =THUR!B59 -> 0 | F55: =FRI!B59 -> 0 | G55: =SAT!B59 -> 0 | H55: =SUN!B59 -> 0 | I55: =SUM(I47:I54) -> 0
A57: =MON!A61 -> ACCOUNTS | B57: =MON!B61 -> MONDAY | C57: =TUES!B61 -> TUESDAY | D57: =WED!B61 -> WEDNESDAY | E57: =THUR!B61 -> THURSDAY | F57: =FRI!B61 -> FRIDAY | G57: =SAT!B61 -> SATURDAY | H57: =SUN!B61 -> SUNDAY | I57: =I3 -> TOTAL
A58: =MON!A62 -> Studio Account Name | B58: =MON!B62 -> Amount | C58: =TUES!B62 -> Amount | D58: =WED!B62 -> Amount | E58: =THUR!B62 -> Amount | F58: =FRI!B62 -> Amount | G58: =SAT!B62 -> Amount | H58: =SUN!B62 -> Amount
B59: =MON!B63 -> 0 | C59: =TUES!B63 -> 0 | D59: =WED!B63 -> 0 | E59: =THUR!B63 -> 0 | F59: =FRI!B63 -> 0 | G59: =SAT!B63 -> 0 | H59: =SUN!B63 -> 0 | I59: =SUM(B59:H59) -> 0
A60: =MON!A64 -> Gift Cards | B60: =MON!B64 -> 0 | C60: =TUES!B64 -> 0 | D60: =WED!B64 -> 0 | E60: =THUR!B64 -> 0 | F60: =FRI!B64 -> 0 | G60: =SAT!B64 -> 0 | H60: =SUN!B64 -> 0 | I60: =SUM(B60:H60) -> 0
A61: =MON!A65 -> Total | B61: =MON!B65 -> 0 | C61: =TUES!B65 -> 0 | D61: =WED!B65 -> 0 | E61: =THUR!B65 -> 0 | F61: =FRI!B65 -> 0 | G61: =SAT!B65 -> 0 | H61: =SUN!B65 -> 0 | I61: =SUM(I59:I60) -> 0
A63: =MON!A67 -> SALES | B63: =MON!B67 -> MONDAY | C63: =TUES!B67 -> TUESDAY | D63: =WED!B67 -> WEDNESDAY | E63: =THUR!B67 -> THURSDAY | F63: =FRI!B67 -> FRIDAY | G63: =SAT!B67 -> SATURDAY | H63: =SUN!B67 -> SUNDAY | I63: =I3 -> TOTAL
A64: =MON!A68 -> Coffee | B64: =MON!B68 -> 0 | C64: =TUES!B68 -> 0 | D64: =WED!B68 -> 0 | E64: =THUR!B68 -> 0 | F64: =FRI!B68 -> 0 | G64: =SAT!B68 -> 0 | H64: =SUN!B68 -> 0 | I64: =SUM(B64:H64) -> 0
A65: =MON!A69 -> Food | B65: =MON!B69 -> 0 | C65: =TUES!B69 -> 0 | D65: =WED!B69 -> 0 | E65: =THUR!B69 -> 0 | F65: =FRI!B69 -> 0 | G65: =SAT!B69 -> 0 | H65: =SUN!B69 -> 0 | I65: =SUM(B65:H65) -> 0
A66: =MON!A70 -> Soft Drinks | B66: =MON!B70 -> 0 | C66: =TUES!B70 -> 0 | D66: =WED!B70 -> 0 | E66: =THUR!B70 -> 0 | F66: =FRI!B70 -> 0 | G66: =SAT!B70 -> 0 | H66: =SUN!B70 -> 0 | I66: =SUM(B66:H66) -> 0
A67: =MON!A71 -> Alcohol | B67: =MON!B71 -> 0 | C67: =TUES!B71 -> 0 | D67: =WED!B71 -> 0 | E67: =THUR!B71 -> 0 | F67: =FRI!B71 -> 0 | G67: =SAT!B71 -> 0 | H67: =SUN!B71 -> 0 | I67: =SUM(B67:H67) -> 0
A68: =MON!A72 -> Retail | B68: =MON!B72 -> 0 | C68: =TUES!B72 -> 0 | D68: =WED!B72 -> 0 | E68: =THUR!B72 -> 0 | F68: =FRI!B72 -> 0 | G68: =SAT!B72 -> 0 | H68: =SUN!B72 -> 0 | I68: =SUM(B68:H68) -> 0
A69: =MON!A73 -> Room Hire | B69: =MON!B73 -> 0 | C69: =TUES!B73 -> 0 | D69: =WED!B73 -> 0 | E69: =THUR!B73 -> 0 | F69: =FRI!B73 -> 0 | G69: =SAT!B73 -> 0 | H69: =SUN!B73 -> 0 | I69: =SUM(B69:H69) -> 0
A70: VAT | B70: =MON!B74 -> 0 | C70: =TUES!B74 -> 0 | D70: =WED!B74 -> 0 | E70: =THUR!B74 -> 0 | F70: =FRI!B74 -> 0 | G70: =SAT!B74 -> 0 | H70: =SUN!B74 -> 0 | I70: =SUM(B70:H70) -> 0
A71: =MON!A75 -> Total | B71: =MON!B75 -> 0 | C71: =TUES!B75 -> 0 | D71: =WED!B75 -> 0 | E71: =THUR!B75 -> 0 | F71: =FRI!B75 -> 0 | G71: =SAT!B75 -> 0 | H71: =SUN!B75 -> 0 | I71: =SUM(I64:I69) -> 0
A73: =MON!A77 -> Cash Banked | B73: =MON!B77 -> 0 | C73: =TUES!B77 -> 0 | D73: =WED!B77 -> 0 | E73: =THUR!B77 -> 0 | F73: =FRI!B77 -> 0 | G73: =SAT!B77 -> 0 | H73: =SUN!B77 -> 0 | I73: =SUM(B73:H73) -> 0
A74: =MON!A78 -> Z Read 1 | B74: =MON!B78 -> 0 | C74: =TUES!B78 -> 0 | D74: =WED!B78 -> 0 | E74: =THUR!B78 -> 0 | F74: =FRI!B78 -> 0 | G74: =SAT!B78 -> 0 | H74: =SUN!B78 -> 0 | I74: =SUM(B74:H74) -> 0
A75: =MON!A79 -> Z Read 2 | B75: =MON!B79 -> 0 | C75: =TUES!B79 -> 0 | D75: =WED!B79 -> 0 | E75: =THUR!B79 -> 0 | F75: =FRI!B79 -> 0 | G75: =SAT!B79 -> 0 | H75: =SUN!B79 -> 0 | I75: =SUM(B75:H75) -> 0
A76: =MON!A80 -> Z Read 3 | B76: =MON!B80 -> 0 | C76: =TUES!B80 -> 0 | D76: =WED!B80 -> 0 | E76: =THUR!B80 -> 0 | F76: =FRI!B80 -> 0 | G76: =SAT!B80 -> 0 | H76: =SUN!B80 -> 0 | I76: =SUM(B76:H76) -> 0
A77: =MON!A81 -> Accounts | B77: =MON!B81 -> 0 | C77: =TUES!B81 -> 0 | D77: =WED!B81 -> 0 | E77: =THUR!B81 -> 0 | F77: =FRI!B81 -> 0 | G77: =SAT!B81 -> 0 | H77: =SUN!B81 -> 0 | I77: =SUM(B77:H77) -> 0
A78: =MON!A82 -> Receipts | B78: =MON!B82 -> 0 | C78: =TUES!B82 -> 0 | D78: =WED!B82 -> 0 | E78: =THUR!B82 -> 0 | F78: =FRI!B82 -> 0 | G78: =SAT!B82 -> 0 | H78: =SUN!B82 -> 0 | I78: =SUM(B78:H78) -> 0
A79: =MON!A83 -> TOTAL | B79: =MON!B83 -> 0 | C79: =TUES!B83 -> 0 | D79: =WED!B83 -> 0 | E79: =THUR!B83 -> 0 | F79: =FRI!B83 -> 0 | G79: =SAT!B83 -> 0 | H79: =SUN!B83 -> 0 | I79: =SUM(I73:I78) -> 0
A81: Z Read 3
A82: =MON!A85 -> Variance | B82: =MON!B85 -> 0 | C82: =TUES!B85 -> 0 | D82: =WED!B85 -> 0 | E82: =THUR!B85 -> 0 | F82: =FRI!B85 -> 0 | G82: =SAT!B85 -> 0 | H82: =SUN!B85 -> 0 | I82: =SUM(B82:H82) -> 0
A85: =MON!A88 -> BANKED MONEY | B85: =MON!B88 -> MONDAY | C85: =TUES!B88 -> TUESDAY | D85: =WED!B88 -> WEDNESDAY | E85: =THUR!B88 -> THURSDAY | F85: =FRI!B88 -> FRIDAY | G85: =SAT!B88 -> SATURDAY | H85: =SUN!B88 -> SUNDAY | I85: =I3 -> TOTAL
A86: =MON!A89 -> Cash Bag Number | B86: =MON!B89 -> 0 | C86: =TUES!B89 -> 0 | D86: =WED!B89 -> 0 | E86: =THUR!B89 -> 0 | F86: =FRI!B89 -> 0 | G86: =SAT!B89 -> 0 | H86: =SUN!B89 -> 0 | I86: =SUM(B86:H86) -> 0
A87: =MON!A90 -> Cash Paying In Slip | B87: =MON!B90 -> 0 | C87: =TUES!B90 -> 0 | D87: =WED!B90 -> 0 | E87: =THUR!B90 -> 0 | F87: =FRI!B90 -> 0 | G87: =SAT!B90 -> 0 | H87: =SUN!B90 -> 0 | I87: =SUM(B87:H87) -> 0
A88: =MON!A91 -> HSBC Receipt No | B88: =MON!B91 -> 0 | C88: =TUES!B91 -> 0 | D88: =WED!B91 -> 0 | E88: =THUR!B91 -> 0 | F88: =FRI!B91 -> 0 | G88: =SAT!B91 -> 0 | H88: =SUN!B91 -> 0 | I88: =SUM(B88:H88) -> 0
A89: =MON!A92 -> Closing Supervisor | B89: =MON!B92 -> 0 | C89: =TUES!B92 -> 0 | D89: =WED!B92 -> 0 | E89: =THUR!B92 -> 0 | F89: =FRI!B92 -> 0 | G89: =SAT!B92 -> 0 | H89: =SUN!B92 -> 0 | I89: =SUM(B89:H89) -> 0
A90: =MON!A93 -> Date | B90: =MON!B93 -> 0 | C90: =TUES!B93 -> 0 | D90: =WED!B93 -> 0 | E90: =THUR!B93 -> 0 | F90: =FRI!B93 -> 0 | G90: =SAT!B93 -> 0 | H90: =SUN!B93 -> 0 | I90: =SUM(B90:H90) -> 0
A92: =MON!A95 -> DISCOUNTS/COMPS
A93: =MON!A96 -> Comp 1 | B93: =MON!B96 -> 0 | C93: =TUES!B96 -> 0 | D93: =WED!B96 -> 0 | E93: =THUR!B96 -> 0 | F93: =FRI!B96 -> 0 | G93: =SAT!B96 -> 0 | H93: =SUN!B96 -> 0 | I93: =SUM(B93:H93) -> 0
A94: =MON!A97 -> Comp 2 | B94: =MON!B97 -> 0 | C94: =TUES!B97 -> 0 | D94: =WED!B97 -> 0 | E94: =THUR!B97 -> 0 | F94: =FRI!B97 -> 0 | G94: =SAT!B97 -> 0 | H94: =SUN!B97 -> 0 | I94: =SUM(B94:H94) -> 0
A95: =MON!A98 -> Comp 3 | B95: =MON!B98 -> 0 | C95: =TUES!B98 -> 0 | D95: =WED!B98 -> 0 | E95: =THUR!B98 -> 0 | F95: =FRI!B98 -> 0 | G95: =SAT!B98 -> 0 | H95: =SUN!B98 -> 0 | I95: =SUM(B95:H95) -> 0
A96: =MON!A99 -> Comp 4 | B96: =MON!B99 -> 0 | C96: =TUES!B99 -> 0 | D96: =WED!B99 -> 0 | E96: =THUR!B99 -> 0 | F96: =FRI!B99 -> 0 | G96: =SAT!B99 -> 0 | H96: =SUN!B99 -> 0 | I96: =SUM(B96:H96) -> 0
A97: =MON!A100 -> Comp 5 | B97: =MON!B100 -> 0 | C97: =TUES!B100 -> 0 | D97: =WED!B100 -> 0 | E97: =THUR!B100 -> 0 | F97: =FRI!B100 -> 0 | G97: =SAT!B100 -> 0 | H97: =SUN!B100 -> 0 | I97: =SUM(B97:H97) -> 0
A98: =MON!A101 -> Comp 6 | B98: =MON!B101 -> 0 | C98: =TUES!B101 -> 0 | D98: =WED!B101 -> 0 | E98: =THUR!B101 -> 0 | F98: =FRI!B101 -> 0 | G98: =SAT!B101 -> 0 | H98: =SUN!B101 -> 0 | I98: =SUM(B98:H98) -> 0
A99: =MON!A102 -> Comp 7 | B99: =MON!B102 -> 0 | C99: =TUES!B102 -> 0 | D99: =WED!B102 -> 0 | E99: =THUR!B102 -> 0 | F99: =FRI!B102 -> 0 | G99: =SAT!B102 -> 0 | H99: =SUN!B102 -> 0 | I99: =SUM(B99:H99) -> 0
A100: =MON!A103 -> Comp 8 | B100: =MON!B103 -> 0 | C100: =TUES!B103 -> 0 | D100: =WED!B103 -> 0 | E100: =THUR!B103 -> 0 | F100: =FRI!B103 -> 0 | G100: =SAT!B103 -> 0 | H100: =SUN!B103 -> 0 | I100: =SUM(B100:H100) -> 0
A101: =MON!A104 -> Comp 9 | B101: =MON!B104 -> 0 | C101: =TUES!B104 -> 0 | D101: =WED!B104 -> 0 | E101: =THUR!B104 -> 0 | F101: =FRI!B104 -> 0 | G101: =SAT!B104 -> 0 | H101: =SUN!B104 -> 0 | I101: =SUM(B101:H101) -> 0
A102: =MON!A105 -> Comp 10 | B102: =MON!B105 -> 0 | C102: =TUES!B105 -> 0 | D102: =WED!B105 -> 0 | E102: =THUR!B105 -> 0 | F102: =FRI!B105 -> 0 | G102: =SAT!B105 -> 0 | H102: =SUN!B105 -> 0 | I102: =SUM(B102:H102) -> 0
A103: =MON!A106 -> Total Comps | B103: =MON!B106 -> 0 | C103: =TUES!B106 -> 0 | D103: =WED!B106 -> 0 | E103: =THUR!B106 -> 0 | F103: =FRI!B106 -> 0 | G103: =SAT!B106 -> 0 | H103: =SUN!B106 -> 0 | I103: =SUM(I93:I102) -> 0
